Metadata-Version: 2.1
Name: django-daterangefilter-fixed
Version: 1.1.0
Summary: Date range filter for Django admin fixed for django 4.x
Home-page: https://github.com/smirnovv2007/django-daterangefilter/tree/master
Author: Andrey Novikov
Author-email: novikov@gmail.com
License: MIT
Project-URL: Source, https://github.com/smirnovv2007/django-daterangefilter/
Project-URL: Tracker, https://github.com/smirnovv2007/django-daterangefilter/issues
Classifier: Development Status :: 5 - Production/Stable
Classifier: Framework :: Django
Classifier: Programming Language :: Python
Classifier: Programming Language :: Python :: 2
Classifier: Programming Language :: Python :: 3
Classifier: License :: OSI Approved :: MIT License
Classifier: Operating System :: OS Independent
License-File: LICENSE
